LICENSE.txt
MANIFEST.in
setup.cfg
setup.py
tdw/__init__.py
tdw/audio_constants.py
tdw/audio_utils.py
tdw/cardinal_direction.py
tdw/controller.py
tdw/int_pair.py
tdw/librarian.py
tdw/ordinal_direction.py
tdw/output_data.py
tdw/quaternion_utils.py
tdw/remote_build_launcher.py
tdw/tdw_utils.py
tdw/type_aliases.py
tdw/version.py
tdw.egg-info/PKG-INFO
tdw.egg-info/SOURCES.txt
tdw.egg-info/dependency_links.txt
tdw.egg-info/requires.txt
tdw.egg-info/top_level.txt
tdw/FBOutput/AlbedoColors.py
tdw/FBOutput/AudioSource.py
tdw/FBOutput/AudioSourceDone.py
tdw/FBOutput/AudioSources.py
tdw/FBOutput/AvatarKinematic.py
tdw/FBOutput/AvatarNonKinematic.py
tdw/FBOutput/AvatarSegmentationColor.py
tdw/FBOutput/AvatarSimpleBody.py
tdw/FBOutput/AvatarTransformMatrices.py
tdw/FBOutput/Bounds.py
tdw/FBOutput/CameraMatrices.py
tdw/FBOutput/Categories.py
tdw/FBOutput/Category.py
tdw/FBOutput/Collision.py
tdw/FBOutput/CollisionState.py
tdw/FBOutput/Color.py
tdw/FBOutput/ContactPoint.py
tdw/FBOutput/Containment.py
tdw/FBOutput/DirectionalLight.py
tdw/FBOutput/DriveAxis.py
tdw/FBOutput/Drones.py
tdw/FBOutput/DynamicCompositeObjects.py
tdw/FBOutput/DynamicEmptyObjects.py
tdw/FBOutput/DynamicRobots.py
tdw/FBOutput/EnvironmentColliderIntersection.py
tdw/FBOutput/EnvironmentCollision.py
tdw/FBOutput/EulerAngles.py
tdw/FBOutput/Extension.py
tdw/FBOutput/FieldOfView.py
tdw/FBOutput/FlexParticleData.py
tdw/FBOutput/FlexParticles.py
tdw/FBOutput/Fove.py
tdw/FBOutput/Framerate.py
tdw/FBOutput/IdPassGrayscale.py
tdw/FBOutput/IdPassSegmentationColors.py
tdw/FBOutput/ImagePass.py
tdw/FBOutput/ImageSensor.py
tdw/FBOutput/ImageSensors.py
tdw/FBOutput/Images.py
tdw/FBOutput/IsOnNavMesh.py
tdw/FBOutput/JointDrive.py
tdw/FBOutput/JointType.py
tdw/FBOutput/JointVelocities.py
tdw/FBOutput/Junk.py
tdw/FBOutput/Keyboard.py
tdw/FBOutput/LeapMotion.py
tdw/FBOutput/Lights.py
tdw/FBOutput/LocalTransforms.py
tdw/FBOutput/LogMessage.py
tdw/FBOutput/Magnebot.py
tdw/FBOutput/MagnebotWheels.py
tdw/FBOutput/Mesh.py
tdw/FBOutput/Meshes.py
tdw/FBOutput/MessageType.py
tdw/FBOutput/Models.py
tdw/FBOutput/Mouse.py
tdw/FBOutput/NavMeshPath.py
