Metadata-Version: 2.1
Name: tdw
Version: 1.13.0.0
Summary: 3D simulation environment
Home-page: https://github.com/threedworld-mit/tdw
Author: Massachusetts Institute of Technology
Author-email: alters@mit.edu
License: BSD
Keywords: unity simulation ml machine-learning
Classifier: Development Status :: 5 - Production/Stable
Classifier: Intended Audience :: Developers
Classifier: Topic :: Software Development
Classifier: License :: OSI Approved :: BSD License
Classifier: Programming Language :: Python :: 3.6
Classifier: Programming Language :: Python :: 3.7
Classifier: Programming Language :: Python :: 3.8
Classifier: Programming Language :: Python :: 3.9
Classifier: Programming Language :: Python :: 3.10
Classifier: Programming Language :: Python :: 3.11
License-File: LICENSE.txt
Requires-Dist: pyzmq
Requires-Dist: numpy
Requires-Dist: scipy
Requires-Dist: pillow
Requires-Dist: tqdm
Requires-Dist: psutil
Requires-Dist: boto3
Requires-Dist: botocore
Requires-Dist: requests
Requires-Dist: pyinstaller
Requires-Dist: overrides
Requires-Dist: packaging
Requires-Dist: pydub
Requires-Dist: ikpy==3.1
Requires-Dist: screeninfo
Requires-Dist: inflection
